pypdl/__init__.py
pypdl/consumer.py
pypdl/downloader.py
pypdl/producer.py
pypdl/pypdl.py
pypdl/utils.py
pypdl-1.5.7.dist-info/licenses/LICENSE
test/__init__.py
test/server.py
test/test.py
pypdl-1.5.7.dist-info/METADATA
pypdl-1.5.7.dist-info/WHEEL
pypdl-1.5.7.dist-info/top_level.txt
pypdl-1.5.7.dist-info/RECORD
