Metadata-Version: 2.4
Name: pypdl
Version: 1.5.7
Summary: A concurrent pure python download manager
Home-page: https://github.com/mjishnu/pypdl
Author: Jishnu M
Author-email: <mjishnu@proton.me>
License: MIT
Keywords: python,downloader,multi-threaded-downloader,concurrent-downloader,parallel-downloader,async-downloader,asyncronous-downloader,download-manager,fast-downloader,download-accelerator,download-optimizer,download-utility,download-tool,download-automation
Classifier: Operating System :: OS Independent
Classifier: License :: OSI Approved :: MIT License
Classifier: Development Status :: 5 - Production/Stable
Classifier: Programming Language :: Python :: 3
Requires-Python: >=3.8
License-File: LICENSE
Requires-Dist: aiohttp
Requires-Dist: aiofiles
Dynamic: author
Dynamic: author-email
Dynamic: classifier
Dynamic: description
Dynamic: description-content-type
Dynamic: home-page
Dynamic: keywords
Dynamic: license
Dynamic: license-file
Dynamic: requires-dist
Dynamic: requires-python
Dynamic: summary
